{"cameraMode":{"drawMode":0,"name":"Shaded","section":"Shading Mode"},"sceneLighting":true,"audioPlay":false,"sceneViewState":{"showFog":true,"showMaterialUpdate":false,"showSkybox":true,"showFlares":true,"showImageEffects":true,"showParticleSystems":true,"showVisualEffectGraphs":true,"m_FxEnabled":true},"in2DMode":false,"pivot":{"x":475.2794189453125,"y":376.46673583984377,"z":501.7530517578125},"rotation":{"x":-0.06924794614315033,"y":-0.016179926693439485,"z":0.0011140670394524932,"w":-0.9974844455718994},"size":597.734375,"orthographic":false}